aindapy/__init__.py
aindapy/log.py
aindapy/pbar.py
aindapy/settings.py
aindapy-0.0.14.data/data/my_data/data_file
aindapy-0.0.14.dist-info/LICENSE.txt
aindapy-0.0.14.dist-info/METADATA
aindapy-0.0.14.dist-info/WHEEL
aindapy-0.0.14.dist-info/entry_points.txt
aindapy-0.0.14.dist-info/top_level.txt
aindapy-0.0.14.dist-info/RECORD
