Metadata-Version: 2.1
Name: aindapy
Version: 0.0.14
Summary: Ainda Package made for python lovers. This is inteded to be used on ainda private cloud
Home-page: https://bitbucket.org/xsensors/aindapy
Author: Rafael Lima, Edgar Medina
Author-email: 
License: UNKNOWN
Project-URL: Bug Reports, https://bitbucket.org/xsensors/aindapy/issues
Project-URL: Source, https://bitbucket.org/xsensors/aindapy/
Keywords: aindapy,ainda,aindavision.com,aindaanalytics.com
Platform: UNKNOWN
Classifier: Development Status :: 3 - Alpha
Classifier: Intended Audience :: Developers
Classifier: Topic :: Software Development :: Build Tools
Classifier: License :: OSI Approved :: MIT License
Classifier: Programming Language :: Python :: 3
Classifier: Programming Language :: Python :: 3.6
Classifier: Programming Language :: Python :: 3.7
Classifier: Programming Language :: Python :: 3.8
Classifier: Programming Language :: Python :: 3.9
Classifier: Programming Language :: Python :: 3 :: Only
Requires-Python: >=3.6, <4
License-File: LICENSE.txt
Requires-Dist: requests
Requires-Dist: Pillow
Provides-Extra: dev
Requires-Dist: check-manifest ; extra == 'dev'
Provides-Extra: test
Requires-Dist: coverage ; extra == 'test'
